glove/Glove.py
glove/__init__.py
glove/test.py
glove_py-0.1.0.dist-info/METADATA
glove_py-0.1.0.dist-info/WHEEL
glove_py-0.1.0.dist-info/top_level.txt
glove_py-0.1.0.dist-info/RECORD
