Metadata-Version: 2.1
Name: glove-py
Version: 0.1.0
Summary: glove Python bindings
Home-page: https://github.com/f20500909/glove_py
Author: Wang Heng
Author-email: me@lightgoing.com
License: MIT
Platform: UNKNOWN
Classifier: Programming Language :: Python :: 3
Requires-Dist: pybind11 (>=2.2)
Requires-Dist: setuptools (>=0.7.0)
Requires-Dist: numpy
